vein/__init__.py
vein-0.1.0.dist-info/LICENSE
vein-0.1.0.dist-info/METADATA
vein-0.1.0.dist-info/WHEEL
vein-0.1.0.dist-info/RECORD
